<?xml version="1.0" encoding="UTF-8"?>
<objects serializationModel="Studio.02.01.00">
	<object class="AudioFile" id="{e802d9f8-b244-4b28-b82f-cec3d836bc07}">
		<property name="assetPath">
			<value>PinHurtSFX.wav</value>
		</property>
		<property name="frequencyInKHz">
			<value>48</value>
		</property>
		<property name="channelCount">
			<value>2</value>
		</property>
		<property name="length">
			<value>0.168875</value>
		</property>
		<relationship name="masterAssetFolder">
			<destination>{bafd4693-1861-4e66-88a9-f975c259f59f}</destination>
		</relationship>
	</object>
</objects>
